{"Title":null,"OffCanvas":0,"MainToolbar":{"Columns":[{"Title":null,"Tab":null,"Alignment":0,"PrimaryStyle":0,"ResponsiveStyle":0,"Widgets":[{"ToolbarWidgetType":0,"FieldName":"Toolbar.WIPPGITB01020","Icon":{"Color":2,"Size":0,"Name":"play_arrow","Visibility":true,"Alignment":0,"Weight":0,"Tooltip":null},"Tooltip":"Start Processing","ColumnLayout":null,"SubType":null,"Title":"","PrimaryStyle":0,"SecondaryStyle":0,"WidgetName":null,"Collapsible":false,"IsCollapsibleOpen":false,"Border":0,"BackgroundColor":9,"TitleBackground":0,"TitleForeground":0,"Id":"45b328c5-2805-49d7-9a9d-6baa27fdbe58","Index":0,"index":0,"TypeName":"ToolbarWidget","HasChildren":false}],"Id":"07a84b8f-25d2-4e03-ada5-fda3967b935c","Index":0,"index":0,"TypeName":"Column","HasChildren":false},{"Title":null,"Tab":null,"Alignment":1,"PrimaryStyle":0,"ResponsiveStyle":0,"Widgets":[],"Id":"33f5975a-e5d6-4584-9868-0148dd22fc08","Index":1,"index":0,"TypeName":"Column","HasChildren":false}],"IsToolbarVisible":true,"Id":"121b6dfb-df6a-41de-be2f-2a4cf9a73786","Index":0,"index":0,"TypeName":null,"HasChildren":false},"Columns":[{"Title":null,"Tab":null,"Alignment":0,"PrimaryStyle":0,"ResponsiveStyle":3,"Widgets":[{"RowStyle":0,"DisplayStyle":5,"Rows":[{"Columns":[{"Title":null,"Tab":null,"Alignment":0,"PrimaryStyle":0,"ResponsiveStyle":0,"Widgets":[{"IsMandatory":false,"EntryType":7,"FieldName":"  Function","FieldPath":"Fields.WIPPGILVFunctionA","DataType":"4","HasSmartTag":false,"Caption":{"Color":8,"Size":0,"Name":null,"Visibility":true,"Alignment":0,"Weight":0,"Tooltip":null},"Value":{"Color":8,"Size":1,"Name":null,"Visibility":false,"Alignment":0,"Weight":1,"Tooltip":null},"Icon":{"Color":0,"Size":1,"Name":null,"Visibility":false,"Alignment":0,"Weight":0,"Tooltip":null},"KeyAction":"","Keyfield":null,"ColumnLayout":null,"SubType":"","Title":"","PrimaryStyle":0,"SecondaryStyle":0,"WidgetName":null,"Collapsible":false,"IsCollapsibleOpen":false,"Border":0,"BackgroundColor":9,"TitleBackground":0,"TitleForeground":0,"Id":"cef8158e-8162-4385-fbf2-a644456df14e","Index":1,"index":0,"TypeName":"EntryDataWidget","HasChildren":false},{"IsMandatory":false,"EntryType":1,"FieldName":"  To ledger year","FieldPath":"Fields.WIPPGILVToLedgerYear","DataType":"N","HasSmartTag":false,"Caption":{"Color":8,"Size":0,"Name":null,"Visibility":true,"Alignment":0,"Weight":0,"Tooltip":null},"Value":{"Color":8,"Size":1,"Name":null,"Visibility":false,"Alignment":0,"Weight":1,"Tooltip":null},"Icon":{"Color":0,"Size":1,"Name":null,"Visibility":false,"Alignment":0,"Weight":0,"Tooltip":null},"KeyAction":"","Keyfield":null,"ColumnLayout":null,"SubType":"","Title":"","PrimaryStyle":0,"SecondaryStyle":0,"WidgetName":null,"Collapsible":false,"IsCollapsibleOpen":false,"Border":0,"BackgroundColor":9,"TitleBackground":0,"TitleForeground":0,"Id":"6c660b0a-f85e-45aa-a211-a9b5754ca19c","Index":2,"index":1,"TypeName":"EntryDataWidget","HasChildren":false},{"IsMandatory":false,"EntryType":1,"FieldName":"  From ledger month (Ledger month)","FieldPath":"Fields.WIPPGILVLedgerMonth","DataType":"N","HasSmartTag":false,"Caption":{"Color":8,"Size":0,"Name":null,"Visibility":true,"Alignment":0,"Weight":0,"Tooltip":null},"Value":{"Color":8,"Size":1,"Name":null,"Visibility":false,"Alignment":0,"Weight":1,"Tooltip":null},"Icon":{"Color":0,"Size":1,"Name":null,"Visibility":false,"Alignment":0,"Weight":0,"Tooltip":null},"KeyAction":"","Keyfield":null,"ColumnLayout":null,"SubType":"","Title":"","PrimaryStyle":0,"SecondaryStyle":0,"WidgetName":null,"Collapsible":false,"IsCollapsibleOpen":false,"Border":0,"BackgroundColor":9,"TitleBackground":0,"TitleForeground":0,"Id":"5558aa87-4dee-4b6d-d511-7ae8e06cb7fc","Index":3,"index":2,"TypeName":"EntryDataWidget","HasChildren":false},{"IsMandatory":false,"EntryType":10,"FieldName":"  From journal (Journal)","FieldPath":"Fields.WIPPGILVJournal","DataType":"A","HasSmartTag":true,"Caption":{"Color":8,"Size":0,"Name":null,"Visibility":true,"Alignment":0,"Weight":0,"Tooltip":null},"Value":{"Color":8,"Size":1,"Name":null,"Visibility":false,"Alignment":0,"Weight":1,"Tooltip":null},"Icon":{"Color":0,"Size":1,"Name":null,"Visibility":false,"Alignment":0,"Weight":0,"Tooltip":null},"KeyAction":"","Keyfield":null,"ColumnLayout":null,"SubType":"","Title":"","PrimaryStyle":0,"SecondaryStyle":0,"WidgetName":null,"Collapsible":false,"IsCollapsibleOpen":false,"Border":0,"BackgroundColor":9,"TitleBackground":0,"TitleForeground":0,"Id":"a307cfc1-d17a-478a-e899-779cd96c7712","Index":4,"index":3,"TypeName":"EntryDataWidget","HasChildren":false},{"IsMandatory":false,"EntryType":1,"FieldName":"  To ledger year","FieldPath":"Fields.WIPPGILVToLedgerYear","DataType":"N","HasSmartTag":false,"Caption":{"Color":8,"Size":0,"Name":null,"Visibility":true,"Alignment":0,"Weight":0,"Tooltip":null},"Value":{"Color":8,"Size":1,"Name":null,"Visibility":false,"Alignment":0,"Weight":1,"Tooltip":null},"Icon":{"Color":0,"Size":1,"Name":null,"Visibility":false,"Alignment":0,"Weight":0,"Tooltip":null},"KeyAction":"","Keyfield":null,"ColumnLayout":null,"SubType":"","Title":"","PrimaryStyle":0,"SecondaryStyle":0,"WidgetName":null,"Collapsible":false,"IsCollapsibleOpen":false,"Border":0,"BackgroundColor":9,"TitleBackground":0,"TitleForeground":0,"Id":"a8a3699b-cfd4-446a-e39a-96ab0bcd5e5e","Index":5,"index":4,"TypeName":"EntryDataWidget","HasChildren":false},{"IsMandatory":false,"EntryType":1,"FieldName":"  To ledger month","FieldPath":"Fields.WIPPGILVToLedgerMonth","DataType":"N","HasSmartTag":false,"Caption":{"Color":8,"Size":0,"Name":null,"Visibility":true,"Alignment":0,"Weight":0,"Tooltip":null},"Value":{"Color":8,"Size":1,"Name":null,"Visibility":false,"Alignment":0,"Weight":1,"Tooltip":null},"Icon":{"Color":0,"Size":1,"Name":null,"Visibility":false,"Alignment":0,"Weight":0,"Tooltip":null},"KeyAction":"","Keyfield":null,"ColumnLayout":null,"SubType":"","Title":"","PrimaryStyle":0,"SecondaryStyle":0,"WidgetName":null,"Collapsible":false,"IsCollapsibleOpen":false,"Border":0,"BackgroundColor":9,"TitleBackground":0,"TitleForeground":0,"Id":"d75f3571-3acc-402b-e694-f1189b985ccb","Index":6,"index":5,"TypeName":"EntryDataWidget","HasChildren":false},{"IsMandatory":false,"EntryType":10,"FieldName":"  To journal","FieldPath":"Fields.WIPPGILVToJournal","DataType":"A","HasSmartTag":true,"Caption":{"Color":8,"Size":0,"Name":null,"Visibility":true,"Alignment":0,"Weight":0,"Tooltip":null},"Value":{"Color":8,"Size":1,"Name":null,"Visibility":false,"Alignment":0,"Weight":1,"Tooltip":null},"Icon":{"Color":0,"Size":1,"Name":null,"Visibility":false,"Alignment":0,"Weight":0,"Tooltip":null},"KeyAction":"","Keyfield":null,"ColumnLayout":null,"SubType":"","Title":"","PrimaryStyle":0,"SecondaryStyle":0,"WidgetName":null,"Collapsible":false,"IsCollapsibleOpen":false,"Border":0,"BackgroundColor":9,"TitleBackground":0,"TitleForeground":0,"Id":"d9ce5b4d-636f-4541-f0bc-547de8711f0d","Index":7,"index":6,"TypeName":"EntryDataWidget","HasChildren":false}],"Id":"9e78cf8e-2ed1-4095-a304-6c9f49d989ce","Index":0,"index":0,"TypeName":"Column","HasChildren":false}],"Id":"59b9c837-b8c4-48ec-853d-4d692b518541","Index":0,"index":0,"TypeName":"Row","HasChildren":true}],"Tabs":null,"Icon":"layers","ColumnLayout":null,"SubType":"Joined","Title":"Journal options","PrimaryStyle":0,"SecondaryStyle":0,"WidgetName":"1col_form_widget","Collapsible":false,"IsCollapsibleOpen":false,"Border":0,"BackgroundColor":9,"TitleBackground":9,"TitleForeground":8,"Id":"abf49af3-d868-4e8e-9f9b-a3edd967c134","Index":0,"index":1,"TypeName":"LayoutWidget","HasChildren":true},{"RowStyle":0,"DisplayStyle":5,"Rows":[{"Columns":[{"Title":null,"Tab":null,"Alignment":0,"PrimaryStyle":0,"ResponsiveStyle":0,"Widgets":[{"IsMandatory":false,"EntryType":6,"FieldName":"  Close this application","FieldPath":"Fields.WIPPGILVCloseThisApplication","DataType":"B","HasSmartTag":false,"Caption":{"Color":8,"Size":0,"Name":null,"Visibility":true,"Alignment":0,"Weight":0,"Tooltip":null},"Value":{"Color":8,"Size":1,"Name":null,"Visibility":false,"Alignment":0,"Weight":1,"Tooltip":null},"Icon":{"Color":0,"Size":1,"Name":null,"Visibility":false,"Alignment":0,"Weight":0,"Tooltip":null},"KeyAction":"","Keyfield":null,"ColumnLayout":null,"SubType":"","Title":"","PrimaryStyle":0,"SecondaryStyle":0,"WidgetName":null,"Collapsible":false,"IsCollapsibleOpen":false,"Border":0,"BackgroundColor":9,"TitleBackground":0,"TitleForeground":0,"Id":"ffa4a422-b512-456d-8f63-e14e6a70058d","Index":0,"index":0,"TypeName":"EntryDataWidget","HasChildren":false}],"Id":"b629fb88-349b-4d10-80e5-58629170a554","Index":0,"index":0,"TypeName":"Column","HasChildren":false}],"Id":"c639cafa-bff2-4e64-a021-fb2aec02585b","Index":0,"index":0,"TypeName":"Row","HasChildren":true}],"Tabs":null,"Icon":"layers","ColumnLayout":"1col","SubType":"Joined","Title":"After processing completed","PrimaryStyle":0,"SecondaryStyle":0,"WidgetName":"1col_form_widget","Collapsible":true,"IsCollapsibleOpen":false,"Border":0,"BackgroundColor":9,"TitleBackground":9,"TitleForeground":0,"Id":"98bbcda8-abf7-4f9c-cb30-3290d75c3e7e","Index":0,"index":1,"TypeName":"LayoutWidget","HasChildren":true}],"Id":"6ce9c8a5-24c3-49ed-a26f-e75f9df74039","Index":0,"index":0,"TypeName":"Column","HasChildren":false},{"Title":null,"Tab":null,"Alignment":0,"PrimaryStyle":0,"ResponsiveStyle":2,"Widgets":[{"Caption":"WIP Labor Integration Update","Icon":"layers","GridDataFieldName":"WIPPGIL1","Height":0,"ColumnLayout":null,"SubType":null,"Title":"Report","PrimaryStyle":0,"SecondaryStyle":0,"WidgetName":"WIPPGIL1","Collapsible":false,"IsCollapsibleOpen":false,"Border":2,"BackgroundColor":9,"TitleBackground":9,"TitleForeground":8,"Id":"2fa3e8a0-df3e-494a-df74-85b809d88c73","Index":0,"index":0,"TypeName":"GridList","HasChildren":false}],"Id":"fc07b758-bfad-4dcd-9ef4-99db1ef4c493","Index":1,"index":0,"TypeName":"Column","HasChildren":false}],"HelpTourContent":null,"WindowDetails":null,"OffCanvasLayouts":{},"Id":"c30f5f9e-badd-4ed9-8e10-dc3aec498ffd","Index":0,"index":0,"TypeName":null,"HasChildren":false}